pyxote/__init__.py
pyxote/command_serializer.py
pyxote/installer.py
pyxote/package_checker.py
pyxote/package_installer.py
pyxote-0.1.0.dist-info/LICENSE
pyxote-0.1.0.dist-info/METADATA
pyxote-0.1.0.dist-info/WHEEL
pyxote-0.1.0.dist-info/RECORD
